README.md
setup.py
alphorder/__init__.py
alphorder/__main__.py
alphorder/sorter.py
alphorder.egg-info/PKG-INFO
alphorder.egg-info/SOURCES.txt
alphorder.egg-info/dependency_links.txt
alphorder.egg-info/entry_points.txt
alphorder.egg-info/top_level.txt