Metadata-Version: 2.1
Name: alphorder
Version: 0.1.1
Summary: Sort a folder's content with just one line of code
Home-page: https://github.com/riolp9991/alphorder
Author: riolp9991
Author-email: riolp9991@gmail.com
License: MIT
Platform: UNKNOWN
Classifier: Programming Language :: Python :: 3
Classifier: License :: OSI Approved :: MIT License
Classifier: Operating System :: OS Independent
Requires-Python: >=3.6
